recommendation_model_server/__init__.py
recommendation_model_server/__main__.py
recommendation_model_server/elastic/all_results.json
recommendation_model_server/elastic/all_text_fields.json
recommendation_model_server/elastic/naive.json
recommendation_model_server/elastic/restaurants.json
recommendation_model_server/endpoints/__init__.py
recommendation_model_server/endpoints/autocomplete.py
recommendation_model_server/endpoints/index.py
recommendation_model_server/endpoints/predict.py
recommendation_model_server/endpoints/search.py
recommendation_model_server/features.py
recommendation_model_server/indexer.py
recommendation_model_server/model.py
recommendation_model_server/py.typed
recommendation_model_server/ratings.py
recommendation_model_server/recommendation_api.py
recommendation_model_server/restaurant.py
recommendation_model_server/search.py
recommendation_model_server/server.py
recommendation_model_server/transformations.py
recommendation_model_server/utils.py
recommendation_model_server-0.1.1.dist-info/WHEEL
recommendation_model_server-0.1.1.dist-info/METADATA
recommendation_model_server-0.1.1.dist-info/RECORD
