Metadata-Version: 2.1
Name: recommendation-model-server
Version: 0.1.1
Summary: A real-time inference server
License: MIT
Author: Rauan Akylzhanov
Author-email: akylzhanov.r@gmail.com
Requires-Python: ==3.10.10
Classifier: License :: OSI Approved :: MIT License
Classifier: Programming Language :: Python :: 3
Requires-Dist: elasticsearch (==7.13.3)
Requires-Dist: fastapi (>=0.92.0,<0.93.0)
Requires-Dist: fastapi-utils (>=0.2.1,<0.3.0)
Requires-Dist: httpx (>=0.23.3,<0.24.0)
Requires-Dist: invokust (>=0.77,<0.78)
Requires-Dist: jinja2 (>=3.1.2,<4.0.0)
Requires-Dist: joblib (>=1.2.0,<2.0.0)
Requires-Dist: lightgbm (>=3.3.5,<4.0.0)
Requires-Dist: pandas (>=1.5.3,<2.0.0)
Requires-Dist: polars (>=0.16.6,<0.17.0)
Requires-Dist: pyarrow (>=11.0.0,<12.0.0)
Requires-Dist: pydantic (>=1.10.5,<2.0.0)
Requires-Dist: python-multipart (>=0.0.6,<0.0.7)
Requires-Dist: twine (>=4.0.2,<5.0.0)
Requires-Dist: types-requests (>=2.28.11.14,<3.0.0.0)
Requires-Dist: uvicorn (>=0.20.0,<0.21.0)
